adaptix/__init__.py
adaptix/load_error.py
adaptix/py.typed
adaptix/retort.py
adaptix/struct_trail.py
adaptix/_internal/__init__.py
adaptix/_internal/common.py
adaptix/_internal/compat.py
adaptix/_internal/datastructures.py
adaptix/_internal/definitions.py
adaptix/_internal/feature_requirement.py
adaptix/_internal/name_style.py
adaptix/_internal/py.typed
adaptix/_internal/special_cases_optimization.py
adaptix/_internal/struct_trail.py
adaptix/_internal/utils.py
adaptix/_internal/code_tools/__init__.py
adaptix/_internal/code_tools/ast_templater.py
adaptix/_internal/code_tools/cascade_namespace.py
adaptix/_internal/code_tools/code_block_tree.py
adaptix/_internal/code_tools/code_builder.py
adaptix/_internal/code_tools/compiler.py
adaptix/_internal/code_tools/name_sanitizer.py
adaptix/_internal/code_tools/utils.py
adaptix/_internal/conversion/__init__.py
adaptix/_internal/conversion/coercer_provider.py
adaptix/_internal/conversion/converter_provider.py
adaptix/_internal/conversion/linking_provider.py
adaptix/_internal/conversion/model_coercer_provider.py
adaptix/_internal/conversion/policy_provider.py
adaptix/_internal/conversion/provider_template.py
adaptix/_internal/conversion/request_cls.py
adaptix/_internal/conversion/request_filtering.py
adaptix/_internal/conversion/broaching/__init__.py
adaptix/_internal/conversion/broaching/code_generator.py
adaptix/_internal/conversion/broaching/definitions.py
adaptix/_internal/conversion/facade/__init__.py
adaptix/_internal/conversion/facade/checker.py
adaptix/_internal/conversion/facade/func.py
adaptix/_internal/conversion/facade/provider.py
adaptix/_internal/conversion/facade/retort.py
adaptix/_internal/integrations/__init__.py
adaptix/_internal/integrations/msgspec/__init__.py
adaptix/_internal/integrations/msgspec/native.py
adaptix/_internal/integrations/pydantic/__init__.py
adaptix/_internal/integrations/pydantic/native.py
adaptix/_internal/integrations/sqlalchemy/__init__.py
adaptix-3.0.0b10.dist-info/LICENSE
adaptix-3.0.0b10.dist-info/METADATA
adaptix-3.0.0b10.dist-info/WHEEL
adaptix-3.0.0b10.dist-info/top_level.txt
adaptix-3.0.0b10.dist-info/RECORD
