Metadata-Version: 2.1
Name: adaptix
Version: 3.0.0b10
Summary: An extremely flexible and configurable data model conversion library
Author-email: "A. Tikhonov" <17@itishka.org>
Project-URL: Homepage, https://github.com/reagento/adaptix
Project-URL: Bug Tracker, https://github.com/reagento/adaptix/issues
Project-URL: Documentation, https://adaptix.readthedocs.io/en/latest/
Project-URL: Changelog, https://adaptix.readthedocs.io/en/latest/reference/changelog.html
Project-URL: Source, https://github.com/reagento/adaptix/
Project-URL: Download, https://github.com/reagento/adaptix/#files
Classifier: Development Status :: 3 - Alpha
Classifier: Programming Language :: Python :: 3
Classifier: Programming Language :: Python :: 3.9
Classifier: Programming Language :: Python :: 3.10
Classifier: Programming Language :: Python :: 3.11
Classifier: Programming Language :: Python :: 3.12
Classifier: Programming Language :: Python :: 3.13
Classifier: Programming Language :: Python :: Implementation :: CPython
Classifier: Programming Language :: Python :: Implementation :: PyPy
Classifier: Operating System :: OS Independent
Classifier: Intended Audience :: Developers
Classifier: Intended Audience :: Information Technology
Classifier: Intended Audience :: System Administrators
Classifier: License :: OSI Approved :: Apache Software License
Classifier: Typing :: Typed
Classifier: Topic :: Software Development :: Libraries :: Python Modules
Classifier: Topic :: Internet
Requires-Python: >=3.9
License-File: LICENSE
Requires-Dist: exceptiongroup>=1.1.3; python_version < "3.11"
Provides-Extra: attrs
Requires-Dist: attrs>=21.3.0; extra == "attrs"
Provides-Extra: attrs-strict
Requires-Dist: attrs<=24.2.0,>=21.3.0; extra == "attrs-strict"
Provides-Extra: sqlalchemy
Requires-Dist: sqlalchemy>=2.0.0; extra == "sqlalchemy"
Provides-Extra: sqlalchemy-strict
Requires-Dist: sqlalchemy<=2.0.40,>=2.0.0; extra == "sqlalchemy-strict"
Provides-Extra: pydantic
Requires-Dist: pydantic>=2.0.0; extra == "pydantic"
Provides-Extra: pydantic-strict
Requires-Dist: pydantic<=2.11.3,>=2.0.0; extra == "pydantic-strict"
Provides-Extra: msgspec
Requires-Dist: msgspec>=0.18.5; extra == "msgspec"
Provides-Extra: msgspec-strict
Requires-Dist: msgspec<=0.19.0,>=0.18.5; extra == "msgspec-strict"
